{
  "aliasColors": {},
  "bars": false,
  "dashLength": 10,
  "dashes": false,
  "datasource": "test-cluster",
  "decimals": 1,
  "fill": 1,
  "gridPos": {
    "h": 7,
    "w": 12,
    "x": 0,
    "y": 40
  },
  "id": 105,
  "legend": {
    "alignAsTable": true,
    "avg": false,
    "current": true,
    "max": true,
    "min": false,
    "rightSide": true,
    "show": true,
    "sideWidth": 350,
    "total": false,
    "values": true,
    "sort": "max",
    "sortDesc": true
  },
  "lines": true,
  "linewidth": 1,
  "links": [],
  "nullPointMode": "null",
  "percentage": false,
  "pointradius": 5,
  "points": false,
  "renderer": "flot",
  "seriesOverrides": [],
  "spaceLength": 10,
  "stack": false,
  "steppedLine": false,
  "targets": [
    {
      "expr": "topk(10, sum(rate(tikv_thread_cpu_seconds_total{instance=~\"$instance\", name=~\"grpc_server.*\"}[1m])) by (instance, name))",
      "format": "time_series",
      "intervalFactor": 2,
      "legendFormat": "{{instance}}-{{name}}",
      "refId": "A",
      "step": 4
    }
  ],
  "thresholds": [],
  "timeFrom": null,
  "timeShift": null,
  "title": "gRPC poll CPU",
  "tooltip": {
    "shared": true,
    "sort": 0,
    "value_type": "individual"
  },
  "type": "graph",
  "xaxis": {
    "buckets": null,
    "mode": "time",
    "name": null,
    "show": true,
    "values": []
  },
  "yaxes": [
    {
      "format": "percentunit",
      "label": null,
      "logBase": 1,
      "max": null,
      "min": null,
      "show": true
    },
    {
      "format": "short",
      "label": null,
      "logBase": 1,
      "max": null,
      "min": null,
      "show": true
    }
  ],
  "yaxis": {
    "align": false,
    "alignLevel": null
  },
  "timeRegions": []
}
